<?xml version="1.0" encoding="utf-8" ?><dwsync><file name="tripsmart_styles.css" server="G:/tripsmart_yourlastname/" local="129739823260000000" remote="129739823260000000" Dst="1" /><file name="index.html" server="G:/tripsmart_yourlastname/" local="129749537820000000" remote="129749537820000000" Dst="1" /><file name="airplane.ico" server="G:/tripsmart_yourlastname/" local="129187777380000000" remote="129187777380000000" Dst="1" /><file name="catalog.html" server="G:/tripsmart_yourlastname/" local="129739882500000000" remote="129739882500000000" Dst="1" /><file name="galapagos.html" server="G:/tripsmart_yourlastname/" local="129726960080000000" remote="129726960080000000" Dst="1" /><file name="HTML5_thrColFixHdr.css" server="G:/tripsmart_yourlastname/" local="129739813260000000" remote="129739813260000000" Dst="1" /><file name="newsletter.html" server="G:/tripsmart_yourlastname/" local="129749537820000000" remote="129749537820000000" Dst="1" /><file name="peru.html" server="G:/tripsmart_yourlastname/" local="129727087780000000" remote="129727087780000000" Dst="1" /><file name="tours.html" server="G:/tripsmart_yourlastname/" local="129728028360000000" remote="129728028360000000" Dst="1" /><file name="airplane.ico" server="Macintosh HD/Users/andy/Sites/ivc/htdocs/tripsmart/" local="3357156138" remote="319783739001021226" Dst="-1" /><file name="catalog.html" server="Macintosh HD/Users/andy/Sites/ivc/htdocs/tripsmart/" local="3447904478" remote="319783739091769566" Dst="-1" /><file name="galapagos.html" server="Macintosh HD/Users/andy/Sites/ivc/htdocs/tripsmart/" local="3447904240" remote="319783739091769328" Dst="-1" /><file name="HTML5_thrColFixHdr.css" server="Macintosh HD/Users/andy/Sites/ivc/htdocs/tripsmart/" local="3447904845" remote="319783739091769933" Dst="-1" /><file name="index.html" server="Macintosh HD/Users/andy/Sites/ivc/htdocs/tripsmart/" local="3447904613" remote="319783739091769701" Dst="-1" /><file name="newsletter.html" server="Macintosh HD/Users/andy/Sites/ivc/htdocs/tripsmart/" local="3447904292" remote="319783739091769380" Dst="-1" /><file name="peru.html" server="Macintosh HD/Users/andy/Sites/ivc/htdocs/tripsmart/" local="3447904311" remote="319783739091769399" Dst="-1" /><file name="services.html" server="Macintosh HD/Users/andy/Sites/ivc/htdocs/tripsmart/" local="3447904323" remote="319783739091769411" Dst="-1" /><file name="tours.html" server="Macintosh HD/Users/andy/Sites/ivc/htdocs/tripsmart/" local="3447904334" remote="319783739091769422" Dst="-1" /><file name="tripsmart_styles.css" server="Macintosh HD/Users/andy/Sites/ivc/htdocs/tripsmart/" local="3447904478" remote="319783739091769566" Dst="-1" /><file name="airplane.ico" server="st3w.ivc.edu//rmathur/cim243-2/aelster0/tripsmart/" local="3357156138" remote="319783739091771808" Dst="-1" /><file name="catalog.html" server="st3w.ivc.edu//rmathur/cim243-2/aelster0/tripsmart/" local="3447906934" remote="319783739091772048" Dst="-1" /><file name="galapagos.html" server="st3w.ivc.edu//rmathur/cim243-2/aelster0/tripsmart/" local="3447904240" remote="319783739091771808" Dst="-1" /><file name="HTML5_thrColFixHdr.css" server="st3w.ivc.edu//rmathur/cim243-2/aelster0/tripsmart/" local="3447904845" remote="319783739091771808" Dst="-1" /><file name="index.html" server="st3w.ivc.edu//rmathur/cim243-2/aelster0/tripsmart/" local="3447904613" remote="319783739091771808" Dst="-1" /><file name="newsletter.html" server="st3w.ivc.edu//rmathur/cim243-2/aelster0/tripsmart/" local="3447904292" remote="319783739091771808" Dst="-1" /><file name="peru.html" server="st3w.ivc.edu//rmathur/cim243-2/aelster0/tripsmart/" local="3447904311" remote="319783739091771808" Dst="-1" /><file name="services.html" server="st3w.ivc.edu//rmathur/cim243-2/aelster0/tripsmart/" local="3447904323" remote="319783739091771808" Dst="-1" /><file name="tours.html" server="st3w.ivc.edu//rmathur/cim243-2/aelster0/tripsmart/" local="3447904334" remote="319783739091771808" Dst="-1" /><file name="tripsmart_styles.css" server="st3w.ivc.edu//rmathur/cim243-2/aelster0/tripsmart/" local="3447904478" remote="319783739091771808" Dst="-1" /></dwsync>